telellm/__init__.py
telellm/chat_template.json
telellm/llmservice.py
telellm/requirements-gpu.txt
telellm/service.py
telellm/check/__init__.py
telellm/check/chat_checker.py
telellm/config/__init__.py
telellm/config/config.py
telellm/config/const.py
telellm/fncall/__init__.py
telellm/fncall/base_fncall_prompt.py
telellm/fncall/glm_fncall_prompt.py
telellm/fncall/qwen_fncall_prompt.py
telellm/infer/__init__.py
telellm/infer/chat_infer.py
telellm/models/__init__.py
telellm/models/chat_model.py
telellm/models/model.py
telellm/routers/__init__.py
telellm/routers/chat_completion.py
telellm/routers/health.py
telellm/routers/models.py
telellm/routers/version.py
telellm/servers/__init__.py
telellm/servers/fastapi_server.py
telellm/status/__init__.py
telellm/status/http_status.py
telellm/status/status_exception.py
telellm/utils/__init__.py
telellm/utils/fastapi_utils.py
telellm/utils/logger_utils.py
telellm/utils/rest_utils.py
telellm_tool/__init__.py
telellm_tool/telellm.py
telellm_tool/cmd/__init__.py
telellm_tool/cmd/cmd.py
telellm_tool/cmd/service.py
telellm_tool/cmd/eval_cmd/evaluate_chat_ceval.py
telellm_tool/cmd/eval_cmd/evaluate_chat_gsm8k.py
telellm_tool/cmd/eval_cmd/evaluate_chat_humaneval.py
telellm_tool/cmd/eval_cmd/evaluate_chat_mmlu.py
telellm_tool/cmd/eval_cmd/dataset/ceval/test/accountant_test.csv
telellm_tool/cmd/eval_cmd/dataset/ceval/test/advanced_mathematics_test.csv
telellm_tool/cmd/eval_cmd/dataset/ceval/test/art_studies_test.csv
telellm_tool/cmd/eval_cmd/dataset/ceval/test/basic_medicine_test.csv
telellm_tool/cmd/eval_cmd/dataset/ceval/test/business_administration_test.csv
telellm_tool/cmd/eval_cmd/dataset/ceval/test/chinese_language_and_literature_test.csv
telellm_tool/cmd/eval_cmd/dataset/ceval/test/civil_servant_test.csv
telellm_tool/cmd/eval_cmd/dataset/ceval/test/clinical_medicine_test.csv
telellm_tool/cmd/eval_cmd/dataset/ceval/test/college_chemistry_test.csv
telellm_tool/cmd/eval_cmd/dataset/ceval/test/college_economics_test.csv
telellm-0.1.2.dist-info/LICENSE
telellm-0.1.2.dist-info/METADATA
telellm-0.1.2.dist-info/NOTICE
telellm-0.1.2.dist-info/WHEEL
telellm-0.1.2.dist-info/entry_points.txt
telellm-0.1.2.dist-info/top_level.txt
telellm-0.1.2.dist-info/RECORD
