Metadata-Version: 2.1
Name: telellm
Version: 0.1.2
Summary: A high-throughput and memory-efficient inference and serving engine for LLMs
Home-page: https://gitee.com/modelers/telellm
Author: State Cloud Intelligent Computing Team
License: Apache 2.0
Classifier: Programming Language :: Python :: 3.8
Classifier: Programming Language :: Python :: 3.9
Classifier: Programming Language :: Python :: 3.10
Classifier: Programming Language :: Python :: 3.11
Classifier: Programming Language :: Python :: 3.12
Classifier: License :: OSI Approved :: Apache Software License
Classifier: Topic :: Scientific/Engineering :: Artificial Intelligence
Requires-Python: >=3.9
License-File: LICENSE
License-File: NOTICE
Requires-Dist: psutil
Requires-Dist: sentencepiece
Requires-Dist: numpy<2.0.0
Requires-Dist: requests
Requires-Dist: tqdm
Requires-Dist: py-cpuinfo
Requires-Dist: tokenizers>=0.19.1
Requires-Dist: protobuf
Requires-Dist: fastapi
Requires-Dist: aiohttp
Requires-Dist: openai>=1.0
Requires-Dist: uvicorn[standard]
Requires-Dist: pydantic>=2.8
Requires-Dist: pillow
Requires-Dist: prometheus-client>=0.18.0
Requires-Dist: tiktoken>=0.6.0
Requires-Dist: outlines<0.1,>=0.0.43
Requires-Dist: typing-extensions>=4.10
Requires-Dist: filelock>=3.10.4
Requires-Dist: pyzmq
Requires-Dist: msgspec
Requires-Dist: librosa
Requires-Dist: soundfile
Requires-Dist: gguf==0.9.1
Requires-Dist: importlib-metadata
Requires-Dist: ray>=2.9
Requires-Dist: sse-starlette
Requires-Dist: cmake>=3.26
Requires-Dist: Click>=8.0.4
Requires-Dist: rsa==4.9
Requires-Dist: requests==2.31.0
Requires-Dist: Jinja2==3.1.4
Requires-Dist: numpy==1.26.0
Requires-Dist: thefuzz==0.22.1
Requires-Dist: pandas==2.2.2
Requires-Dist: tqdm==4.66.4
Requires-Dist: easydict==1.13
Requires-Dist: pytest
Requires-Dist: transformers==4.43.2
Requires-Dist: torch==2.1.0
Requires-Dist: torchvision==0.16.0
Requires-Dist: torch-npu==2.1.0.post8.dev20241015
Provides-Extra: tensorizer
Requires-Dist: tensorizer>=2.9.0; extra == "tensorizer"
